mypackage/__init__.py
mypackage/mymodule.py
mypackage/template.txt
ProductionalizingProject_1-0.23.3.dist-info/METADATA
ProductionalizingProject_1-0.23.3.dist-info/WHEEL
ProductionalizingProject_1-0.23.3.dist-info/entry_points.txt
ProductionalizingProject_1-0.23.3.dist-info/top_level.txt
ProductionalizingProject_1-0.23.3.dist-info/RECORD
