Metadata-Version: 2.1
Name: ProductionalizingProject-1
Version: 0.23.3
Summary: A very simple setuptools-pyproject.toml project
Author-email: Advanced Python <python@developintelligence.com>
Requires-Dist: numpy (>=1.16)
